pypoman/__init__.py
pypoman/bretl.py
pypoman/duality.py
pypoman/intersection.py
pypoman/lp.py
pypoman/misc.py
pypoman/polygon.py
pypoman/polyhedron.py
pypoman/projection.py
pypoman-1.1.1.dist-info/LICENSE
pypoman-1.1.1.dist-info/WHEEL
pypoman-1.1.1.dist-info/METADATA
pypoman-1.1.1.dist-info/RECORD
