Metadata-Version: 2.1
Name: pypoman
Version: 1.1.1
Summary: Python module for polyhedral geometry.
Keywords: convex, polyhedron, polyhedra, polytope, projection, duality
Author-email: Stéphane Caron <stephane.caron@normalesup.org>
Maintainer-email: Stéphane Caron <stephane.caron@normalesup.org>
Requires-Python: >=3.7
Classifier: Development Status :: 5 - Production/Stable
Classifier: Intended Audience :: Developers
Classifier: Intended Audience :: Science/Research
Classifier: License :: OSI Approved :: GNU General Public License v3 (GPLv3)
Classifier: Operating System :: OS Independent
Classifier: Programming Language :: Python :: 3.7
Classifier: Programming Language :: Python :: 3.8
Classifier: Programming Language :: Python :: 3.9
Classifier: Programming Language :: Python :: 3.10
Classifier: Topic :: Scientific/Engineering :: Mathematics
Classifier: Intended Audience :: Developers
Classifier: Intended Audience :: Science/Research
Requires-Dist: cvxopt >=1.2.6
Requires-Dist: matplotlib >=3.3.4
Requires-Dist: numpy >=1.15.4
Requires-Dist: pycddlib >=2.1.4,<3
Requires-Dist: scipy >=1.7.0
Requires-Dist: pyclipper >=1.3.0 ; extra == "all"
Requires-Dist: qpsolvers >=3.3.1 ; extra == "all"
Project-URL: Changelog, https://github.com/stephane-caron/pypoman/blob/main/CHANGELOG.md
Project-URL: Documentation, https://scaron.info/doc/pypoman/
Project-URL: Homepage, https://github.com/stephane-caron/pypoman
Project-URL: Source, https://github.com/stephane-caron/pypoman
Project-URL: Tracker, https://github.com/stephane-caron/pypoman/issues
Provides-Extra: all
